MANIFEST.in
README.rst
setup.py
fakeemail/__init__.py
fakeemail/server.py
fakeemail/smtp_server.py
fakeemail/web_server.py
fakeemail.egg-info/PKG-INFO
fakeemail.egg-info/SOURCES.txt
fakeemail.egg-info/dependency_links.txt
fakeemail.egg-info/entry_points.txt
fakeemail.egg-info/requires.txt
fakeemail.egg-info/top_level.txt
fakeemail.egg-info/zip-safe
fakeemail/templates/base.html
fakeemail/templates/data_home_page.html
fakeemail/templates/data_message_display.html
fakeemail/templates/home_page.html
fakeemail/templates/message_display.html
twisted/plugins/__init__.py
twisted/plugins/fakeemail.py