Metadata-Version: 1.0
Name: fakeemail
Version: 0.10.0
Summary: A fake Email Server with a Web Front End
Home-page: https://github.com/tomwardill/FakeEmail
Author: Tom Wardill
Author-email: tom@howrandom.net
License: UNKNOWN
Platform: UNKNOWN
